audiobox_aesthetics/__init__.py
audiobox_aesthetics/cli.py
audiobox_aesthetics/infer.py
audiobox_aesthetics/utils.py
audiobox_aesthetics/model/__init__.py
audiobox_aesthetics/model/aes.py
audiobox_aesthetics/model/utils.py
audiobox_aesthetics/model/wavlm.py
audiobox_aesthetics-0.0.4.dist-info/licenses/LICENSE
audiobox_aesthetics-0.0.4.dist-info/METADATA
audiobox_aesthetics-0.0.4.dist-info/WHEEL
audiobox_aesthetics-0.0.4.dist-info/entry_points.txt
audiobox_aesthetics-0.0.4.dist-info/top_level.txt
audiobox_aesthetics-0.0.4.dist-info/RECORD
