Metadata-Version: 2.4
Name: audiobox_aesthetics
Version: 0.0.4
Summary: Unified automatic quality assessment for speech, music, and sound.
Author: Andros Tjandra, Yi-Chiao Wu, Baishan Guo, John Hoffman, Brian Ellis, Apoorv Vyas, Bowen Shi, Sanyuan Chen, Matt Le, Nick Zacharov, Carleigh Wood, Ann Lee, Wei-ning Hsu
Maintainer-email: Andros Tjandra <androstj@meta.com>
License: Attribution 4.0 International
Project-URL: Homepage, https://github.com/facebookresearch/audiobox-aesthetics
Project-URL: Issues, https://github.com/facebookresearch/audiobox-aesthetics/issues
Classifier: Programming Language :: Python :: 3
Classifier: Operating System :: OS Independent
Requires-Python: >=3.9
License-File: LICENSE
Requires-Dist: numpy
Requires-Dist: torch>=2.2.0
Requires-Dist: torchaudio
Requires-Dist: tqdm
Requires-Dist: submitit
Requires-Dist: huggingface_hub
Requires-Dist: rich>=13.9.4
Requires-Dist: safetensors>=0.5.3
Dynamic: license-file
